CtfLingyuZhinan/README.md
CtfLingyuZhinan/__init__.py
CtfLingyuZhinan/__main__.py
CtfLingyuZhinan/file.epub
CtfLingyuZhinan/index.html
CtfLingyuZhinan/css/__init__.py
CtfLingyuZhinan/css/annotations.css
CtfLingyuZhinan/css/main.css
CtfLingyuZhinan/css/normalize.css
CtfLingyuZhinan/css/popup.css
CtfLingyuZhinan/font/__init__.py
CtfLingyuZhinan/font/fontello.eot
CtfLingyuZhinan/font/fontello.svg
CtfLingyuZhinan/font/fontello.ttf
CtfLingyuZhinan/font/fontello.woff
CtfLingyuZhinan/img/__init__.py
CtfLingyuZhinan/img/annotator-glyph-sprite.png
CtfLingyuZhinan/img/annotator-icon-sprite.png
CtfLingyuZhinan/img/apple-touch-icon.png
CtfLingyuZhinan/img/cancelfullscreen.png
CtfLingyuZhinan/img/close.png
CtfLingyuZhinan/img/fullscreen.png
CtfLingyuZhinan/img/loader.gif
CtfLingyuZhinan/img/menu-icon.png
CtfLingyuZhinan/img/save.png
CtfLingyuZhinan/img/saved.png
CtfLingyuZhinan/img/settings-s.png
CtfLingyuZhinan/img/settings.png
CtfLingyuZhinan/img/star.png
CtfLingyuZhinan/js/__init__.py
CtfLingyuZhinan/js/epub.js
CtfLingyuZhinan/js/epub.min.js
CtfLingyuZhinan/js/epub.min.map
CtfLingyuZhinan/js/hooks.min.js
CtfLingyuZhinan/js/hooks.min.map
CtfLingyuZhinan/js/reader.js
CtfLingyuZhinan/js/reader.js.map
CtfLingyuZhinan/js/reader.min.js
CtfLingyuZhinan/js/reader.min.map
CtfLingyuZhinan/js/hooks/__init__.py
CtfLingyuZhinan/js/hooks/extensions/__init__.py
CtfLingyuZhinan/js/hooks/extensions/highlight.js
CtfLingyuZhinan/js/libs/__init__.py
CtfLingyuZhinan/js/libs/jquery.min.js
CtfLingyuZhinan/js/libs/localforage.min.js
CtfLingyuZhinan/js/libs/screenfull.js
CtfLingyuZhinan/js/libs/screenfull.min.js
CtfLingyuZhinan/js/libs/zip.min.js
CtfLingyuZhinan/js/plugins/__init__.py
CtfLingyuZhinan/js/plugins/hypothesis.js
CtfLingyuZhinan/js/plugins/search.js
ctf_lingyu_zhinan-2024.3.2.0.dist-info/METADATA
ctf_lingyu_zhinan-2024.3.2.0.dist-info/WHEEL
ctf_lingyu_zhinan-2024.3.2.0.dist-info/entry_points.txt
ctf_lingyu_zhinan-2024.3.2.0.dist-info/top_level.txt
ctf_lingyu_zhinan-2024.3.2.0.dist-info/RECORD
